sdb_connector-0.2.31.dist-info/METADATA
sdb_connector-0.2.31.dist-info/WHEEL
sdb_connector/__init__.py
sdb_connector/sdb_connector.cpython-311-aarch64-linux-gnu.so
sdb_connector-0.2.31.dist-info/RECORD
