Metadata-Version: 2.3
Name: sdb_connector
Version: 0.2.31
Summary: A python libary written in Rust for Surrealdb connection and data preparation
Author-email: fabian <fabian.lieb@peptech.de>
Requires-Python: >=3.11
